odoo/addons/stock_move_line_dates/README.rst
odoo/addons/stock_move_line_dates/__init__.py
odoo/addons/stock_move_line_dates/__manifest__.py
odoo/addons/stock_move_line_dates/i18n/es.po
odoo/addons/stock_move_line_dates/i18n/it.po
odoo/addons/stock_move_line_dates/i18n/stock_move_line_dates.pot
odoo/addons/stock_move_line_dates/models/__init__.py
odoo/addons/stock_move_line_dates/models/stock_move_line.py
odoo/addons/stock_move_line_dates/readme/CONTEXT.md
odoo/addons/stock_move_line_dates/readme/CONTRIBUTORS.md
odoo/addons/stock_move_line_dates/readme/DESCRIPTION.md
odoo/addons/stock_move_line_dates/readme/USAGE.md
odoo/addons/stock_move_line_dates/static/description/icon.png
odoo/addons/stock_move_line_dates/static/description/index.html
odoo/addons/stock_move_line_dates/views/stock_move_line_view.xml
odoo_addon_stock_move_line_dates-16.0.1.0.1.2.dist-info/METADATA
odoo_addon_stock_move_line_dates-16.0.1.0.1.2.dist-info/WHEEL
odoo_addon_stock_move_line_dates-16.0.1.0.1.2.dist-info/top_level.txt
odoo_addon_stock_move_line_dates-16.0.1.0.1.2.dist-info/RECORD
